cumulocitypython/__init__.py
cumulocitypython/connection.py
cumulocitypython-0.1.7.dist-info/LICENSE.txt
cumulocitypython-0.1.7.dist-info/METADATA
cumulocitypython-0.1.7.dist-info/WHEEL
cumulocitypython-0.1.7.dist-info/top_level.txt
cumulocitypython-0.1.7.dist-info/RECORD
